glaze/Glaze.py
glaze/__init__.py
glaze_cloak-0.1.0.dist-info/LICENSE
glaze_cloak-0.1.0.dist-info/METADATA
glaze_cloak-0.1.0.dist-info/WHEEL
glaze_cloak-0.1.0.dist-info/top_level.txt
glaze_cloak-0.1.0.dist-info/RECORD
